{
  "CityArea" : [
    {
      "label" : "台北市",
      "value" : "台北市",
      "disabled" : false,
      "children" : [
        {
          "label" : "松山區",
          "value" : "松山區",
          "disabled" : false
        },
        {
          "label" : "大安區",
          "value" : "大安區",
          "disabled" : false
        },
        {
          "label" : "中山區",
          "value" : "中山區",
          "disabled" : false
        },
        {
          "label" : "信義區",
          "value" : "信義區",
          "disabled" : false
        },
        {
          "label" : "內湖區",
          "value" : "內湖區",
          "disabled" : false
        },
        {
          "label" : "南港區",
          "value" : "南港區",
          "disabled" : false
        },
        {
          "label" : "士林區",
          "value" : "士林區",
          "disabled" : false
        },
        {
          "label" : "中正區",
          "value" : "中正區",
          "disabled" : false
        },
        {
          "label" : "萬華區",
          "value" : "萬華區",
          "disabled" : false
        },
        {
          "label" : "北投區",
          "value" : "北投區",
          "disabled" : false
        },
        {
          "label" : "文山區",
          "value" : "文山區",
          "disabled" : false
        },
        {
          "label" : "大同區",
          "value" : "大同區",
          "disabled" : false
        }
      ]
    },
    {
      "label" : "新北市",
      "value" : "新北市",
      "disabled" : false,
      "children" : [
        {
          "label" : "淡水區",
          "value" : "淡水區",
          "disabled" : false
        },
        {
          "label" : "林口區",
          "value" : "林口區",
          "disabled" : false
        },
        {
          "label" : "新莊區",
          "value" : "新莊區",
          "disabled" : false
        },
        {
          "label" : "三重區",
          "value" : "三重區",
          "disabled" : false
        },
        {
          "label" : "板橋區",
          "value" : "板橋區",
          "disabled" : false
        },
        {
          "label" : "中和區",
          "value" : "中和區",
          "disabled" : false
        },
        {
          "label" : "新店區",
          "value" : "新店區",
          "disabled" : false
        },
        {
          "label" : "汐止區",
          "value" : "汐止區",
          "disabled" : false
        },
        {
          "label" : "五股區",
          "value" : "五股區",
          "disabled" : false
        },
        {
          "label" : "土城區",
          "value" : "土城區",
          "disabled" : false
        },
        {
          "label" : "永和區",
          "value" : "永和區",
          "disabled" : false
        },
        {
          "label" : "鶯歌區",
          "value" : "鶯歌區",
          "disabled" : false
        },
        {
          "label" : "蘆洲區",
          "value" : "蘆洲區",
          "disabled" : false
        },
        {
          "label" : "八里區",
          "value" : "八里區",
          "disabled" : false
        },
        {
          "label" : "樹林區",
          "value" : "樹林區",
          "disabled" : false
        },
        {
          "label" : "三峽區",
          "value" : "三峽區",
          "disabled" : false
        },
        {
          "label" : "泰山區",
          "value" : "泰山區",
          "disabled" : false
        },
        {
          "label" : "金山區",
          "value" : "金山區",
          "disabled" : false
        },
        {
          "label" : "深坑區",
          "value" : "深坑區",
          "disabled" : false
        },
        {
          "label" : "瑞芳區",
          "value" : "瑞芳區",
          "disabled" : false
        },
        {
          "label" : "三芝區",
          "value" : "三芝區",
          "disabled" : false
        },
        {
          "label" : "平溪區",
          "value" : "平溪區",
          "disabled" : false
        },
        {
          "label" : "石門區",
          "value" : "石門區",
          "disabled" : false
        },
        {
          "label" : "雙溪區",
          "value" : "雙溪區",
          "disabled" : false
        },
        {
          "label" : "坪林區",
          "value" : "坪林區",
          "disabled" : false
        },
        {
          "label" : "烏來區",
          "value" : "烏來區",
          "disabled" : false
        },
        {
          "label" : "石碇區",
          "value" : "石碇區",
          "disabled" : false
        },
        {
          "label" : "萬里區",
          "value" : "萬里區",
          "disabled" : false
        },
        {
          "label" : "貢寮區",
          "value" : "貢寮區",
          "disabled" : false
        }
      ]
    },
    {
      "label" : "桃園市",
      "value" : "桃園市",
      "disabled" : false,
      "children" : [
        {
          "label" : "桃園區",
          "value" : "桃園區",
          "disabled" : false
        },
        {
          "label" : "中壢區",
          "value" : "中壢區",
          "disabled" : false
        },
        {
          "label" : "平鎮區",
          "value" : "平鎮區",
          "disabled" : false
        },
        {
          "label" : "八德區",
          "value" : "八德區",
          "disabled" : false
        },
        {
          "label" : "楊梅區",
          "value" : "楊梅區",
          "disabled" : false
        },
        {
          "label" : "蘆竹區",
          "value" : "蘆竹區",
          "disabled" : false
        },
        {
          "label" : "大溪區",
          "value" : "大溪區",
          "disabled" : false
        },
        {
          "label" : "龍潭區",
          "value" : "龍潭區",
          "disabled" : false
        },
        {
          "label" : "龜山區",
          "value" : "龜山區",
          "disabled" : false
        },
        {
          "label" : "大園區",
          "value" : "大園區",
          "disabled" : false
        },
        {
          "label" : "觀音區",
          "value" : "觀音區",
          "disabled" : false
        },
        {
          "label" : "新屋區",
          "value" : "新屋區",
          "disabled" : false
        },
        {
          "label" : "復興區",
          "value" : "復興區",
          "disabled" : false
        }
      ]
    },
    {
      "label" : "台中市",
      "value" : "台中市",
      "disabled" : false,
      "children" : [
        {
          "label" : "中區",
          "value" : "中區",
          "disabled" : false
        },
        {
          "label" : "東區",
          "value" : "東區",
          "disabled" : false
        },
        {
          "label" : "南區",
          "value" : "南區",
          "disabled" : false
        },
        {
          "label" : "西區",
          "value" : "西區",
          "disabled" : false
        },
        {
          "label" : "北區",
          "value" : "北區",
          "disabled" : false
        },
        {
          "label" : "北屯區",
          "value" : "北屯區",
          "disabled" : false
        },
        {
          "label" : "西屯區",
          "value" : "西屯區",
          "disabled" : false
        },
        {
          "label" : "南屯區",
          "value" : "南屯區",
          "disabled" : false
        },
        {
          "label" : "太平區",
          "value" : "太平區",
          "disabled" : false
        },
        {
          "label" : "大里區",
          "value" : "大里區",
          "disabled" : false
        },
        {
          "label" : "霧峰區",
          "value" : "霧峰區",
          "disabled" : false
        },
        {
          "label" : "烏日區",
          "value" : "烏日區",
          "disabled" : false
        },
        {
          "label" : "豐原區",
          "value" : "豐原區",
          "disabled" : false
        },
        {
          "label" : "后里區",
          "value" : "后里區",
          "disabled" : false
        },
        {
          "label" : "石岡區",
          "value" : "石岡區",
          "disabled" : false
        },
        {
          "label" : "東勢區",
          "value" : "東勢區",
          "disabled" : false
        },
        {
          "label" : "新社區",
          "value" : "新社區",
          "disabled" : false
        },
        {
          "label" : "潭子區",
          "value" : "潭子區",
          "disabled" : false
        },
        {
          "label" : "大雅區",
          "value" : "大雅區",
          "disabled" : false
        },
        {
          "label" : "神岡區",
          "value" : "神岡區",
          "disabled" : false
        },
        {
          "label" : "大肚區",
          "value" : "大肚區",
          "disabled" : false
        },
        {
          "label" : "沙鹿區",
          "value" : "沙鹿區",
          "disabled" : false
        },
        {
          "label" : "龍井區",
          "value" : "龍井區",
          "disabled" : false
        },
        {
          "label" : "梧棲區",
          "value" : "梧棲區",
          "disabled" : false
        },
        {
          "label" : "清水區",
          "value" : "清水區",
          "disabled" : false
        },
        {
          "label" : "大甲區",
          "value" : "大甲區",
          "disabled" : false
        },
        {
          "label" : "外埔區",
          "value" : "外埔區",
          "disabled" : false
        },
        {
          "label" : "大安區",
          "value" : "大安區",
          "disabled" : false
        },
        {
          "label" : "和平區",
          "value" : "和平區",
          "disabled" : false
        }
      ]
    },
    {
      "label" : "台南市",
      "value" : "台南市",
      "disabled" : false,
      "children" : [
        {
          "label" : "中西區",
          "value" : "中西區",
          "disabled" : false
        },
        {
          "label" : "東區",
          "value" : "東區",
          "disabled" : false
        },
        {
          "label" : "南區",
          "value" : "南區",
          "disabled" : false
        },
        {
          "label" : "北區",
          "value" : "北區",
          "disabled" : false
        },
        {
          "label" : "安平區",
          "value" : "安平區",
          "disabled" : false
        },
        {
          "label" : "安南區",
          "value" : "安南區",
          "disabled" : false
        },
        {
          "label" : "永康區",
          "value" : "永康區",
          "disabled" : false
        },
        {
          "label" : "歸仁區",
          "value" : "歸仁區",
          "disabled" : false
        },
        {
          "label" : "新化區",
          "value" : "新化區",
          "disabled" : false
        },
        {
          "label" : "左鎮區",
          "value" : "左鎮區",
          "disabled" : false
        },
        {
          "label" : "玉井區",
          "value" : "玉井區",
          "disabled" : false
        },
        {
          "label" : "楠西區",
          "value" : "楠西區",
          "disabled" : false
        },
        {
          "label" : "南化區",
          "value" : "南化區",
          "disabled" : false
        },
        {
          "label" : "仁德區",
          "value" : "仁德區",
          "disabled" : false
        },
        {
          "label" : "關廟區",
          "value" : "關廟區",
          "disabled" : false
        },
        {
          "label" : "龍崎區",
          "value" : "龍崎區",
          "disabled" : false
        },
        {
          "label" : "官田區",
          "value" : "官田區",
          "disabled" : false
        },
        {
          "label" : "麻豆區",
          "value" : "麻豆區",
          "disabled" : false
        },
        {
          "label" : "佳里區",
          "value" : "佳里區",
          "disabled" : false
        },
        {
          "label" : "西港區",
          "value" : "西港區",
          "disabled" : false
        },
        {
          "label" : "七股區",
          "value" : "七股區",
          "disabled" : false
        },
        {
          "label" : "將軍區",
          "value" : "將軍區",
          "disabled" : false
        },
        {
          "label" : "學甲區",
          "value" : "學甲區",
          "disabled" : false
        },
        {
          "label" : "北門區",
          "value" : "北門區",
          "disabled" : false
        },
        {
          "label" : "新營區",
          "value" : "新營區",
          "disabled" : false
        },
        {
          "label" : "後壁區",
          "value" : "後壁區",
          "disabled" : false
        },
        {
          "label" : "白河區",
          "value" : "白河區",
          "disabled" : false
        },
        {
          "label" : "東山區",
          "value" : "東山區",
          "disabled" : false
        },
        {
          "label" : "六甲區",
          "value" : "六甲區",
          "disabled" : false
        },
        {
          "label" : "下營區",
          "value" : "下營區",
          "disabled" : false
        },
        {
          "label" : "柳營區",
          "value" : "柳營區",
          "disabled" : false
        },
        {
          "label" : "鹽水區",
          "value" : "鹽水區",
          "disabled" : false
        },
        {
          "label" : "善化區",
          "value" : "善化區",
          "disabled" : false
        },
        {
          "label" : "大內區",
          "value" : "大內區",
          "disabled" : false
        },
        {
          "label" : "山上區",
          "value" : "山上區",
          "disabled" : false
        },
        {
          "label" : "新市區",
          "value" : "新市區",
          "disabled" : false
        },
        {
          "label" : "安定區",
          "value" : "安定區",
          "disabled" : false
        }
      ]
    },
    {
      "label" : "高雄市",
      "value" : "高雄市",
      "disabled" : false,
      "children" : [
        {
          "label" : "楠梓區",
          "value" : "楠梓區",
          "disabled" : false
        },
        {
          "label" : "左營區",
          "value" : "左營區",
          "disabled" : false
        },
        {
          "label" : "鼓山區",
          "value" : "鼓山區",
          "disabled" : false
        },
        {
          "label" : "三民區",
          "value" : "三民區",
          "disabled" : false
        },
        {
          "label" : "鹽埕區",
          "value" : "鹽埕區",
          "disabled" : false
        },
        {
          "label" : "前金區",
          "value" : "前金區",
          "disabled" : false
        },
        {
          "label" : "新興區",
          "value" : "新興區",
          "disabled" : false
        },
        {
          "label" : "苓雅區",
          "value" : "苓雅區",
          "disabled" : false
        },
        {
          "label" : "前鎮區",
          "value" : "前鎮區",
          "disabled" : false
        },
        {
          "label" : "旗津區",
          "value" : "旗津區",
          "disabled" : false
        },
        {
          "label" : "小港區",
          "value" : "小港區",
          "disabled" : false
        },
        {
          "label" : "鳳山區",
          "value" : "鳳山區",
          "disabled" : false
        },
        {
          "label" : "大寮區",
          "value" : "大寮區",
          "disabled" : false
        },
        {
          "label" : "鳥松區",
          "value" : "鳥松區",
          "disabled" : false
        },
        {
          "label" : "林園區",
          "value" : "林園區",
          "disabled" : false
        },
        {
          "label" : "仁武區",
          "value" : "仁武區",
          "disabled" : false
        },
        {
          "label" : "大樹區",
          "value" : "大樹區",
          "disabled" : false
        },
        {
          "label" : "大社區",
          "value" : "大社區",
          "disabled" : false
        },
        {
          "label" : "岡山區",
          "value" : "岡山區",
          "disabled" : false
        },
        {
          "label" : "路竹區",
          "value" : "路竹區",
          "disabled" : false
        },
        {
          "label" : "橋頭區",
          "value" : "橋頭區",
          "disabled" : false
        },
        {
          "label" : "梓官區",
          "value" : "梓官區",
          "disabled" : false
        },
        {
          "label" : "彌陀區",
          "value" : "彌陀區",
          "disabled" : false
        },
        {
          "label" : "永安區",
          "value" : "永安區",
          "disabled" : false
        },
        {
          "label" : "燕巢區",
          "value" : "燕巢區",
          "disabled" : false
        },
        {
          "label" : "田寮區",
          "value" : "田寮區",
          "disabled" : false
        },
        {
          "label" : "阿蓮區",
          "value" : "阿蓮區",
          "disabled" : false
        },
        {
          "label" : "茄萣區",
          "value" : "茄萣區",
          "disabled" : false
        },
        {
          "label" : "湖內區",
          "value" : "湖內區",
          "disabled" : false
        },
        {
          "label" : "旗山區",
          "value" : "旗山區",
          "disabled" : false
        },
        {
          "label" : "美濃區",
          "value" : "美濃區",
          "disabled" : false
        },
        {
          "label" : "內門區",
          "value" : "內門區",
          "disabled" : false
        },
        {
          "label" : "杉林區",
          "value" : "杉林區",
          "disabled" : false
        },
        {
          "label" : "甲仙區",
          "value" : "甲仙區",
          "disabled" : false
        },
        {
          "label" : "六龜區",
          "value" : "六龜區",
          "disabled" : false
        },
        {
          "label" : "茂林區",
          "value" : "茂林區",
          "disabled" : false
        },
        {
          "label" : "桃源區",
          "value" : "桃源區",
          "disabled" : false
        },
        {
          "label" : "那瑪夏區",
          "value" : "那瑪夏區",
          "disabled" : false
        }
      ]
    },
    {
      "label" : "基隆市",
      "value" : "基隆市",
      "disabled" : false,
      "children" : [
        {
          "label" : "仁愛區",
          "value" : "仁愛區",
          "disabled" : false
        },
        {
          "label" : "中正區",
          "value" : "中正區",
          "disabled" : false
        },
        {
          "label" : "信義區",
          "value" : "信義區",
          "disabled" : false
        },
        {
          "label" : "中山區",
          "value" : "中山區",
          "disabled" : false
        },
        {
          "label" : "安樂區",
          "value" : "安樂區",
          "disabled" : false
        },
        {
          "label" : "暖暖區",
          "value" : "暖暖區",
          "disabled" : false
        },
        {
          "label" : "七堵區",
          "value" : "七堵區",
          "disabled" : false
        }
      ]
    },
    {
      "label" : "新竹市",
      "value" : "新竹市",
      "disabled" : false,
      "children" : [
        {
          "label" : "東區",
          "value" : "東區",
          "disabled" : false
        },
        {
          "label" : "北區",
          "value" : "北區",
          "disabled" : false
        },
        {
          "label" : "香山區",
          "value" : "香山區",
          "disabled" : false
        }
      ]
    },
    {
      "label" : "嘉義市",
      "value" : "嘉義市",
      "disabled" : false,
      "children" : [
        {
          "label" : "東區",
          "value" : "東區",
          "disabled" : false
        },
        {
          "label" : "西區",
          "value" : "西區",
          "disabled" : false
        }
      ]
    },
    {
      "label" : "新竹縣",
      "value" : "新竹縣",
      "disabled" : false,
      "children" : [
        {
          "label" : "竹北市",
          "value" : "竹北市",
          "disabled" : false
        },
        {
          "label" : "竹東鎮",
          "value" : "竹東鎮",
          "disabled" : false
        },
        {
          "label" : "新埔鎮",
          "value" : "新埔鎮",
          "disabled" : false
        },
        {
          "label" : "關西鎮",
          "value" : "關西鎮",
          "disabled" : false
        },
        {
          "label" : "湖口鄉",
          "value" : "湖口鄉",
          "disabled" : false
        },
        {
          "label" : "新豐鄉",
          "value" : "新豐鄉",
          "disabled" : false
        },
        {
          "label" : "峨眉鄉",
          "value" : "峨眉鄉",
          "disabled" : false
        },
        {
          "label" : "寶山鄉",
          "value" : "寶山鄉",
          "disabled" : false
        },
        {
          "label" : "北埔鄉",
          "value" : "北埔鄉",
          "disabled" : false
        },
        {
          "label" : "芎林鄉",
          "value" : "芎林鄉",
          "disabled" : false
        },
        {
          "label" : "橫山鄉",
          "value" : "橫山鄉",
          "disabled" : false
        },
        {
          "label" : "尖石鄉",
          "value" : "尖石鄉",
          "disabled" : false
        },
        {
          "label" : "五峰鄉",
          "value" : "五峰鄉",
          "disabled" : false
        }
      ]
    },
    {
      "label" : "苗栗縣",
      "value" : "苗栗縣",
      "disabled" : false,
      "children" : [
        {
          "label" : "苗栗市",
          "value" : "苗栗市",
          "disabled" : false
        },
        {
          "label" : "頭份市",
          "value" : "頭份市",
          "disabled" : false
        },
        {
          "label" : "竹南鎮",
          "value" : "竹南鎮",
          "disabled" : false
        },
        {
          "label" : "後龍鎮",
          "value" : "後龍鎮",
          "disabled" : false
        },
        {
          "label" : "通霄鎮",
          "value" : "通霄鎮",
          "disabled" : false
        },
        {
          "label" : "苑裡鎮",
          "value" : "苑裡鎮",
          "disabled" : false
        },
        {
          "label" : "卓蘭鎮",
          "value" : "卓蘭鎮",
          "disabled" : false
        },
        {
          "label" : "造橋鄉",
          "value" : "造橋鄉",
          "disabled" : false
        },
        {
          "label" : "西湖鄉",
          "value" : "西湖鄉",
          "disabled" : false
        },
        {
          "label" : "頭屋鄉",
          "value" : "頭屋鄉",
          "disabled" : false
        },
        {
          "label" : "公館鄉",
          "value" : "公館鄉",
          "disabled" : false
        },
        {
          "label" : "銅鑼鄉",
          "value" : "銅鑼鄉",
          "disabled" : false
        },
        {
          "label" : "三義鄉",
          "value" : "三義鄉",
          "disabled" : false
        },
        {
          "label" : "大湖鄉",
          "value" : "大湖鄉",
          "disabled" : false
        },
        {
          "label" : "獅潭鄉",
          "value" : "獅潭鄉",
          "disabled" : false
        },
        {
          "label" : "三灣鄉",
          "value" : "三灣鄉",
          "disabled" : false
        },
        {
          "label" : "南庄鄉",
          "value" : "南庄鄉",
          "disabled" : false
        },
        {
          "label" : "泰安鄉",
          "value" : "泰安鄉",
          "disabled" : false
        }
      ]
    },
    {
      "label" : "彰化縣",
      "value" : "彰化縣",
      "disabled" : false,
      "children" : [
        {
          "label" : "彰化市",
          "value" : "彰化市",
          "disabled" : false
        },
        {
          "label" : "員林市",
          "value" : "員林市",
          "disabled" : false
        },
        {
          "label" : "和美鎮",
          "value" : "和美鎮",
          "disabled" : false
        },
        {
          "label" : "鹿港鎮",
          "value" : "鹿港鎮",
          "disabled" : false
        },
        {
          "label" : "溪湖鎮",
          "value" : "溪湖鎮",
          "disabled" : false
        },
        {
          "label" : "二林鎮",
          "value" : "二林鎮",
          "disabled" : false
        },
        {
          "label" : "田中鎮",
          "value" : "田中鎮",
          "disabled" : false
        },
        {
          "label" : "北斗鎮",
          "value" : "北斗鎮",
          "disabled" : false
        },
        {
          "label" : "花壇鄉",
          "value" : "花壇鄉",
          "disabled" : false
        },
        {
          "label" : "芬園鄉",
          "value" : "芬園鄉",
          "disabled" : false
        },
        {
          "label" : "大村鄉",
          "value" : "大村鄉",
          "disabled" : false
        },
        {
          "label" : "永靖鄉",
          "value" : "永靖鄉",
          "disabled" : false
        },
        {
          "label" : "伸港鄉",
          "value" : "伸港鄉",
          "disabled" : false
        },
        {
          "label" : "線西鄉",
          "value" : "線西鄉",
          "disabled" : false
        },
        {
          "label" : "福興鄉",
          "value" : "福興鄉",
          "disabled" : false
        },
        {
          "label" : "秀水鄉",
          "value" : "秀水鄉",
          "disabled" : false
        },
        {
          "label" : "埔心鄉",
          "value" : "埔心鄉",
          "disabled" : false
        },
        {
          "label" : "埔鹽鄉",
          "value" : "埔鹽鄉",
          "disabled" : false
        },
        {
          "label" : "大城鄉",
          "value" : "大城鄉",
          "disabled" : false
        },
        {
          "label" : "芳苑鄉",
          "value" : "芳苑鄉",
          "disabled" : false
        },
        {
          "label" : "竹塘鄉",
          "value" : "竹塘鄉",
          "disabled" : false
        },
        {
          "label" : "社頭鄉",
          "value" : "社頭鄉",
          "disabled" : false
        },
        {
          "label" : "二水鄉",
          "value" : "二水鄉",
          "disabled" : false
        },
        {
          "label" : "田尾鄉",
          "value" : "田尾鄉",
          "disabled" : false
        },
        {
          "label" : "埤頭鄉",
          "value" : "埤頭鄉",
          "disabled" : false
        },
        {
          "label" : "溪州鄉",
          "value" : "溪州鄉",
          "disabled" : false
        }
      ]
    },
    {
      "label" : "南投縣",
      "value" : "南投縣",
      "disabled" : false,
      "children" : [
        {
          "label" : "南投市",
          "value" : "南投市",
          "disabled" : false
        },
        {
          "label" : "埔里鎮",
          "value" : "埔里鎮",
          "disabled" : false
        },
        {
          "label" : "草屯鎮",
          "value" : "草屯鎮",
          "disabled" : false
        },
        {
          "label" : "竹山鎮",
          "value" : "竹山鎮",
          "disabled" : false
        },
        {
          "label" : "集集鎮",
          "value" : "集集鎮",
          "disabled" : false
        },
        {
          "label" : "名間鄉",
          "value" : "名間鄉",
          "disabled" : false
        },
        {
          "label" : "鹿谷鄉",
          "value" : "鹿谷鄉",
          "disabled" : false
        },
        {
          "label" : "中寮鄉",
          "value" : "中寮鄉",
          "disabled" : false
        },
        {
          "label" : "魚池鄉",
          "value" : "魚池鄉",
          "disabled" : false
        },
        {
          "label" : "國姓鄉",
          "value" : "國姓鄉",
          "disabled" : false
        },
        {
          "label" : "水里鄉",
          "value" : "水里鄉",
          "disabled" : false
        },
        {
          "label" : "信義鄉",
          "value" : "信義鄉",
          "disabled" : false
        },
        {
          "label" : "仁愛鄉",
          "value" : "仁愛鄉",
          "disabled" : false
        }
      ]
    },
    {
      "label" : "雲林縣",
      "value" : "雲林縣",
      "disabled" : false,
      "children" : [
        {
          "label" : "斗六市",
          "value" : "斗六市",
          "disabled" : false
        },
        {
          "label" : "斗南鎮",
          "value" : "斗南鎮",
          "disabled" : false
        },
        {
          "label" : "虎尾鎮",
          "value" : "虎尾鎮",
          "disabled" : false
        },
        {
          "label" : "西螺鎮",
          "value" : "西螺鎮",
          "disabled" : false
        },
        {
          "label" : "土庫鎮",
          "value" : "土庫鎮",
          "disabled" : false
        },
        {
          "label" : "北港鎮",
          "value" : "北港鎮",
          "disabled" : false
        },
        {
          "label" : "林內鄉",
          "value" : "林內鄉",
          "disabled" : false
        },
        {
          "label" : "古坑鄉",
          "value" : "古坑鄉",
          "disabled" : false
        },
        {
          "label" : "大埤鄉",
          "value" : "大埤鄉",
          "disabled" : false
        },
        {
          "label" : "莿桐鄉",
          "value" : "莿桐鄉",
          "disabled" : false
        },
        {
          "label" : "褒忠鄉",
          "value" : "褒忠鄉",
          "disabled" : false
        },
        {
          "label" : "二崙鄉",
          "value" : "二崙鄉",
          "disabled" : false
        },
        {
          "label" : "崙背鄉",
          "value" : "崙背鄉",
          "disabled" : false
        },
        {
          "label" : "麥寮鄉",
          "value" : "麥寮鄉",
          "disabled" : false
        },
        {
          "label" : "臺西鄉",
          "value" : "臺西鄉",
          "disabled" : false
        },
        {
          "label" : "東勢鄉",
          "value" : "東勢鄉",
          "disabled" : false
        },
        {
          "label" : "元長鄉",
          "value" : "元長鄉",
          "disabled" : false
        },
        {
          "label" : "四湖鄉",
          "value" : "四湖鄉",
          "disabled" : false
        },
        {
          "label" : "口湖鄉",
          "value" : "口湖鄉",
          "disabled" : false
        },
        {
          "label" : "水林鄉",
          "value" : "水林鄉",
          "disabled" : false
        }
      ]
    },
    {
      "label" : "嘉義縣",
      "value" : "嘉義縣",
      "disabled" : false,
      "children" : [
        {
          "label" : "太保市",
          "value" : "太保市",
          "disabled" : false
        },
        {
          "label" : "朴子市",
          "value" : "朴子市",
          "disabled" : false
        },
        {
          "label" : "布袋鎮",
          "value" : "布袋鎮",
          "disabled" : false
        },
        {
          "label" : "大林鎮",
          "value" : "大林鎮",
          "disabled" : false
        },
        {
          "label" : "民雄鄉",
          "value" : "民雄鄉",
          "disabled" : false
        },
        {
          "label" : "溪口鄉",
          "value" : "溪口鄉",
          "disabled" : false
        },
        {
          "label" : "新港鄉",
          "value" : "新港鄉",
          "disabled" : false
        },
        {
          "label" : "六腳鄉",
          "value" : "六腳鄉",
          "disabled" : false
        },
        {
          "label" : "東石鄉",
          "value" : "東石鄉",
          "disabled" : false
        },
        {
          "label" : "東石鄉",
          "value" : "東石鄉",
          "disabled" : false
        },
        {
          "label" : "鹿草鄉",
          "value" : "鹿草鄉",
          "disabled" : false
        },
        {
          "label" : "水上鄉",
          "value" : "水上鄉",
          "disabled" : false
        },
        {
          "label" : "中埔鄉",
          "value" : "中埔鄉",
          "disabled" : false
        },
        {
          "label" : "竹崎鄉",
          "value" : "竹崎鄉",
          "disabled" : false
        },
        {
          "label" : "梅山鄉",
          "value" : "梅山鄉",
          "disabled" : false
        },
        {
          "label" : "番路鄉",
          "value" : "番路鄉",
          "disabled" : false
        },
        {
          "label" : "大埔鄉",
          "value" : "大埔鄉",
          "disabled" : false
        },
        {
          "label" : "阿里山鄉",
          "value" : "阿里山鄉",
          "disabled" : false
        }
      ]
    },
    {
      "label" : "屏東縣",
      "value" : "屏東縣",
      "disabled" : false,
      "children" : [
        {
          "label" : "屏東市",
          "value" : "屏東市",
          "disabled" : false
        },
        {
          "label" : "潮州鎮",
          "value" : "潮州鎮",
          "disabled" : false
        },
        {
          "label" : "東港鎮",
          "value" : "東港鎮",
          "disabled" : false
        },
        {
          "label" : "恆春鎮",
          "value" : "恆春鎮",
          "disabled" : false
        },
        {
          "label" : "萬丹鄉",
          "value" : "萬丹鄉",
          "disabled" : false
        },
        {
          "label" : "長治鄉",
          "value" : "長治鄉",
          "disabled" : false
        },
        {
          "label" : "麟洛鄉",
          "value" : "麟洛鄉",
          "disabled" : false
        },
        {
          "label" : "九如鄉",
          "value" : "九如鄉",
          "disabled" : false
        },
        {
          "label" : "里港鄉",
          "value" : "里港鄉",
          "disabled" : false
        },
        {
          "label" : "鹽埔鄉",
          "value" : "鹽埔鄉",
          "disabled" : false
        },
        {
          "label" : "高樹鄉",
          "value" : "高樹鄉",
          "disabled" : false
        },
        {
          "label" : "萬巒鄉",
          "value" : "萬巒鄉",
          "disabled" : false
        },
        {
          "label" : "內埔鄉",
          "value" : "內埔鄉",
          "disabled" : false
        },
        {
          "label" : "竹田鄉",
          "value" : "竹田鄉",
          "disabled" : false
        },
        {
          "label" : "新埤鄉",
          "value" : "新埤鄉",
          "disabled" : false
        },
        {
          "label" : "枋寮鄉",
          "value" : "枋寮鄉",
          "disabled" : false
        },
        {
          "label" : "新園鄉",
          "value" : "新園鄉",
          "disabled" : false
        },
        {
          "label" : "崁頂鄉",
          "value" : "崁頂鄉",
          "disabled" : false
        },
        {
          "label" : "林邊鄉",
          "value" : "林邊鄉",
          "disabled" : false
        },
        {
          "label" : "南州鄉",
          "value" : "南州鄉",
          "disabled" : false
        },
        {
          "label" : "佳冬鄉",
          "value" : "佳冬鄉",
          "disabled" : false
        },
        {
          "label" : "琉球鄉",
          "value" : "琉球鄉",
          "disabled" : false
        },
        {
          "label" : "車城鄉",
          "value" : "車城鄉",
          "disabled" : false
        },
        {
          "label" : "滿州鄉",
          "value" : "滿州鄉",
          "disabled" : false
        },
        {
          "label" : "枋山鄉",
          "value" : "枋山鄉",
          "disabled" : false
        },
        {
          "label" : "霧臺鄉",
          "value" : "霧臺鄉",
          "disabled" : false
        },
        {
          "label" : "白河區",
          "value" : "白河區",
          "disabled" : false
        },
        {
          "label" : "瑪家鄉",
          "value" : "瑪家鄉",
          "disabled" : false
        },
        {
          "label" : "泰武鄉",
          "value" : "泰武鄉",
          "disabled" : false
        },
        {
          "label" : "來義鄉",
          "value" : "來義鄉",
          "disabled" : false
        },
        {
          "label" : "春日鄉",
          "value" : "春日鄉",
          "disabled" : false
        },
        {
          "label" : "獅子鄉",
          "value" : "獅子鄉",
          "disabled" : false
        },
        {
          "label" : "牡丹鄉",
          "value" : "牡丹鄉",
          "disabled" : false
        },
        {
          "label" : "三地門鄉",
          "value" : "三地門鄉",
          "disabled" : false
        }
      ]
    },
    {
      "label" : "宜蘭縣",
      "value" : "宜蘭縣",
      "disabled" : false,
      "children" : [
        {
          "label" : "宜蘭市",
          "value" : "宜蘭市",
          "disabled" : false
        },
        {
          "label" : "頭城鎮",
          "value" : "頭城鎮",
          "disabled" : false
        },
        {
          "label" : "羅東鎮",
          "value" : "羅東鎮",
          "disabled" : false
        },
        {
          "label" : "蘇澳鎮",
          "value" : "蘇澳鎮",
          "disabled" : false
        },
        {
          "label" : "礁溪鄉",
          "value" : "礁溪鄉",
          "disabled" : false
        },
        {
          "label" : "壯圍鄉",
          "value" : "壯圍鄉",
          "disabled" : false
        },
        {
          "label" : "員山鄉",
          "value": "員山鄉",
          "disabled" : false
        },
        {
          "label" : "冬山鄉",
          "value" : "冬山鄉",
          "disabled" : false
        },
        {
          "label" : "五結鄉",
          "value" : "五結鄉",
          "disabled" : false
        },
        {
          "label" : "三星鄉",
          "value" : "三星鄉",
          "disabled" : false
        },
        {
          "label" : "大同鄉",
          "value" : "大同鄉",
          "disabled" : false
        },
        {
          "label" : "南澳鄉",
          "value" : "南澳鄉",
          "disabled" : false
        }
      ]
    },
    {
      "label" : "花蓮縣",
      "value" : "花蓮縣",
      "disabled" : false,
      "children" : [
        {
          "label" : "花蓮市",
          "value" : "花蓮市",
          "disabled" : false
        },
        {
          "label" : "鳳林鎮",
          "value" : "鳳林鎮",
          "disabled" : false
        },
        {
          "label" : "玉里鎮",
          "value" : "玉里鎮",
          "disabled" : false
        },
        {
          "label" : "新城鄉",
          "value" : "新城鄉",
          "disabled" : false
        },
        {
          "label" : "吉安鄉",
          "value" : "吉安鄉",
          "disabled" : false
        },
        {
          "label" : "壽豐鄉",
          "value" : "壽豐鄉",
          "disabled" : false
        },
        {
          "label" : "光復鄉",
          "value" : "光復鄉",
          "disabled" : false
        },
        {
          "label" : "豐濱鄉",
          "value" : "豐濱鄉",
          "disabled" : false
        },
        {
          "label" : "瑞穗鄉",
          "value" : "瑞穗鄉",
          "disabled" : false
        },
        {
          "label" : "富里鄉",
          "value" : "富里鄉",
          "disabled" : false
        },
        {
          "label" : "秀林鄉",
          "value" : "秀林鄉",
          "disabled" : false
        },
        {
          "label" : "萬榮鄉",
          "value" : "萬榮鄉",
          "disabled" : false
        },
        {
          "label" : "卓溪鄉",
          "value" : "卓溪鄉",
          "disabled" : false
        }
      ]
    },
    {
      "label" : "臺東縣",
      "value" : "臺東縣",
      "disabled" : false,
      "children" : [
        {
          "label" : "臺東市",
          "value" : "臺東市",
          "disabled" : false
        },
        {
          "label" : "成功鎮",
          "value" : "成功鎮",
          "disabled" : false
        },
        {
          "label" : "關山鎮",
          "value" : "關山鎮",
          "disabled" : false
        },
        {
          "label" : "長濱鄉",
          "value" : "長濱鄉",
          "disabled" : false
        },
        {
          "label" : "池上鄉",
          "value" : "池上鄉",
          "disabled" : false
        },
        {
          "label" : "東河鄉",
          "value" : "東河鄉",
          "disabled" : false
        },
        {
          "label" : "鹿野鄉",
          "value" : "鹿野鄉",
          "disabled" : false
        },
        {
          "label" : "卑南鄉",
          "value" : "卑南鄉",
          "disabled" : false
        },
        {
          "label" : "大武鄉",
          "value" : "大武鄉",
          "disabled" : false
        },
        {
          "label" : "綠島鄉",
          "value" : "綠島鄉",
          "disabled" : false
        },
        {
          "label" : "太麻里鄉",
          "value" : "太麻里鄉",
          "disabled" : false
        },
        {
          "label" : "海端鄉",
          "value" : "海端鄉",
          "disabled" : false
        },
        {
          "label" : "延平鄉",
          "value" : "延平鄉",
          "disabled" : false
        },
        {
          "label" : "金峰鄉",
          "value" : "金峰鄉",
          "disabled" : false
        },
        {
          "label" : "達仁鄉",
          "value" : "達仁鄉",
          "disabled" : false
        },
        {
          "label" : "蘭嶼鄉",
          "value" : "蘭嶼鄉",
          "disabled" : false
        }
      ]
    },
    {
      "label" : "澎湖縣",
      "value" : "澎湖縣",
      "disabled" : false,
      "children" : [
        {
          "label" : "馬公市",
          "value" : "馬公市",
          "disabled" : false
        },
        {
          "label" : "湖西鄉",
          "value" : "湖西鄉",
          "disabled" : false
        },
        {
          "label" : "白沙鄉",
          "value" : "白沙鄉",
          "disabled" : false
        },
        {
          "label" : "西嶼鄉",
          "value" : "西嶼鄉",
          "disabled" : false
        },
        {
          "label" : "望安鄉",
          "value" : "望安鄉",
          "disabled" : false
        },
        {
          "label" : "七美鄉",
          "value" : "七美鄉",
          "disabled" : false
        }
      ]
    },
    {
      "label" : "金門縣",
      "value" : "金門縣",
      "disabled" : false,
      "children" : [
        {
          "label" : "金城鎮",
          "value" : "金城鎮",
          "disabled" : false
        },
        {
          "label" : "金湖鎮",
          "value" : "金湖鎮",
          "disabled" : false
        },
        {
          "label" : "金沙鎮",
          "value" : "金沙鎮",
          "disabled" : false
        },
        {
          "label" : "金寧鄉",
          "value" : "金寧鄉",
          "disabled" : false
        },
        {
          "label" : "烈嶼鄉",
          "value" : "烈嶼鄉",
          "disabled" : false
        },
        {
          "label" : "烏坵鄉",
          "value" : "烏坵鄉",
          "disabled" : false
        }
      ]
    },
    {
      "label" : "連江縣",
      "value" : "連江縣",
      "disabled" : false,
      "children" : [
        {
          "label" : "南竿鄉",
          "value" : "南竿鄉",
          "disabled" : false
        },
        {
          "label" : "北竿鄉",
          "value" : "北竿鄉",
          "disabled" : false
        },
        {
          "label" : "莒光鄉",
          "value" : "莒光鄉",
          "disabled" : false
        },
        {
          "label" : "東引鄉",
          "value" : "東引鄉",
          "disabled" : false
        }
      ]
    }
  ]
}
